hope/forms.py
hope/models.py
hope/views.py
hope/tokens.py
hope/urls.py
hope/__init__.py
hope/static/hope/package.json
hope/static/hope/css/base.css
hope/templates/hope/account_activated.html
hope/templates/hope/home.html
hope/templates/hope/signup.html
hope/templates/hope/account_activation_email.html
hope/templates/hope/base.html
hope/templates/hope/account_activation_invalid.html
hope/templates/hope/signin.html
hope/templates/hope/signout.html
hope/templates/hope/account_activation_sent.html
django_hope-0.1.0.dist-info/DESCRIPTION.rst
django_hope-0.1.0.dist-info/RECORD
django_hope-0.1.0.dist-info/METADATA
django_hope-0.1.0.dist-info/top_level.txt
django_hope-0.1.0.dist-info/metadata.json
django_hope-0.1.0.dist-info/WHEEL
